mkdocs_enumerate_and_reference/__init__.py
mkdocs_enumerate_and_reference/enumerate.py
mkdocs_enumerate_and_reference/plugin.py
mkdocs_enumerate_and_reference/reference.py
mkdocs_enumerate_and_reference-0.2.0.dist-info/LICENSE.txt
mkdocs_enumerate_and_reference-0.2.0.dist-info/METADATA
mkdocs_enumerate_and_reference-0.2.0.dist-info/WHEEL
mkdocs_enumerate_and_reference-0.2.0.dist-info/entry_points.txt
mkdocs_enumerate_and_reference-0.2.0.dist-info/RECORD
