Metadata-Version: 2.1
Name: mkdocs-enumerate-and-reference
Version: 0.2.0
Summary: Mkdocs plugin for numbering and referencing
License: MIT
Author: Raphaël Mammeri
Author-email: raphael.mammeri@gmail.com
Requires-Python: >=3.9,<4.0
Classifier: License :: OSI Approved :: MIT License
Classifier: Programming Language :: Python :: 3
Classifier: Programming Language :: Python :: 3.9
Classifier: Programming Language :: Python :: 3.10
Classifier: Programming Language :: Python :: 3.11
Classifier: Programming Language :: Python :: 3.12
Requires-Dist: mkdocs (>=1.5.3,<2.0.0)
